pyarrow_hotfix/__about__.py
pyarrow_hotfix/__init__.py
pyarrow_hotfix-0.4.dist-info/METADATA
pyarrow_hotfix-0.4.dist-info/WHEEL
pyarrow_hotfix-0.4.dist-info/licenses/LICENSE.txt
pyarrow_hotfix-0.4.dist-info/RECORD
