Metadata-Version: 2.1
Name: pyarrow-hotfix
Version: 0.4
Project-URL: Documentation, https://github.com/pitrou/pyarrow-hotfix#readme
Project-URL: Issues, https://github.com/pitrou/pyarrow-hotfix/issues
Project-URL: Source, https://github.com/pitrou/pyarrow-hotfix
Author-email: Antoine Pitrou <antoine@python.org>
License: Apache License, Version 2.0
License-File: LICENSE.txt
Classifier: Development Status :: 4 - Beta
Classifier: Operating System :: OS Independent
Classifier: Programming Language :: Python
Classifier: Programming Language :: Python :: 3
Classifier: Programming Language :: Python :: 3.5
Classifier: Programming Language :: Python :: 3.6
Classifier: Programming Language :: Python :: 3.7
Classifier: Programming Language :: Python :: 3.8
Classifier: Programming Language :: Python :: 3.9
Classifier: Programming Language :: Python :: 3.10
Classifier: Programming Language :: Python :: 3.11
Classifier: Programming Language :: Python :: 3.12
Requires-Python: >=3.5
